setup.py
searchable_collection/__init__.py
searchable_collection/collection.py
searchable_collection/item.py
searchable_collection/simple_comparator.py
searchable_collection.egg-info/PKG-INFO
searchable_collection.egg-info/SOURCES.txt
searchable_collection.egg-info/dependency_links.txt
searchable_collection.egg-info/top_level.txt